CoCoMET/__init__.py
CoCoMET/goes_load.py
CoCoMET/goes_tams.py
CoCoMET/goes_tobac.py
CoCoMET/mesonh_calculate_products.py
CoCoMET/mesonh_load.py
CoCoMET/mesonh_moaap.py
CoCoMET/mesonh_tams.py
CoCoMET/mesonh_tobac.py
CoCoMET/mesonhcube.py
CoCoMET/multi_nexrad_load.py
CoCoMET/multi_nexrad_tobac.py
CoCoMET/nexrad_load.py
CoCoMET/nexrad_tobac.py
CoCoMET/post_processor.py
CoCoMET/rams_calculate_products.py
CoCoMET/rams_configure.py
CoCoMET/rams_load.py
CoCoMET/rams_moaap.py
CoCoMET/rams_tams.py
CoCoMET/rams_tobac.py
CoCoMET/ramscube.py
CoCoMET/run_tracker_wrapper.py
CoCoMET/standard_radar_load.py
CoCoMET/standard_radar_tobac.py
CoCoMET/tracker_output_translation_layer.py
CoCoMET/user_interface_layer.py
CoCoMET/wrf_calculate_products.py
CoCoMET/wrf_load.py
CoCoMET/wrf_moaap.py
CoCoMET/wrf_tams.py
CoCoMET/wrf_tobac.py
CoCoMET/wrfcube.py
CoCoMET/MOAAP/__init__.py
CoCoMET/MOAAP/tracking_functions.py
CoCoMET/TAMS/__init__.py
CoCoMET/TAMS/tracking_functions.py
CoCoMET/analysis/__init__.py
CoCoMET/analysis/analysis_object.py
CoCoMET/analysis/calc_var.py
CoCoMET/analysis/calculate_arm_products.py
CoCoMET/analysis/calculate_bulk_cell_statistics.py
CoCoMET/analysis/calculate_convective_properties.py
CoCoMET/analysis/merge_split_detection.py
CoCoMET/analysis/irregularity/convexity.py
CoCoMET/analysis/irregularity/projection_calc_3d.py
CoCoMET/analysis/irregularity/sphericity.py
CoCoMET/tests/create_test_objects.py
CoCoMET/tests/test_cocomet_full.py
CoCoMET/user_utils/__init__.py
CoCoMET/user_utils/bulk_statistics_funcs.py
cocomet-1.0.0.dist-info/licenses/LICENSE
cocomet-1.0.0.dist-info/METADATA
cocomet-1.0.0.dist-info/WHEEL
cocomet-1.0.0.dist-info/top_level.txt
cocomet-1.0.0.dist-info/RECORD
