Metadata-Version: 2.4
Name: CoCoMET
Version: 1.0.0
Summary: Community Convective cloud Model Evaluation Toolkit (CoCoMET)
Author: Hershel Weiner, Calvin Brooks, Jie Xi Li, Siddhant Gupta, Die Wang
Author-email: Travis Hahn <travis.hahn@psu.edu>
License-Expression: BSD-3-Clause
Project-URL: Homepage, https://github.com/ASCENT-BNL/CoCoMET
Project-URL: Issues, https://github.com/ASCENT-BNL/CoCoMET/issues
Classifier: Programming Language :: Python :: 3
Classifier: Operating System :: OS Independent
Requires-Python: >=3.10.0
License-File: LICENSE
Requires-Dist: numpy<=1.26.4
Requires-Dist: numba
Requires-Dist: xarray
Requires-Dist: netCDF4
Requires-Dist: arm-pyart
Requires-Dist: pandas
Requires-Dist: geopandas
Requires-Dist: cftime
Requires-Dist: pyyaml
Requires-Dist: vincenty
Requires-Dist: iris
Requires-Dist: tobac==1.5.3
Requires-Dist: tqdm
Requires-Dist: metpy
Requires-Dist: scikit-image
Dynamic: license-file
